pih2o/__init__.py
pih2o/api.py
pih2o/config.py
pih2o/h2o.py
pih2o/models.py
pih2o/utils.py
pih2o/controls/__init__.py
pih2o/controls/pump.py
pih2o/controls/sensor.py
pih2o-1.0.3.dist-info/DESCRIPTION.rst
pih2o-1.0.3.dist-info/METADATA
pih2o-1.0.3.dist-info/RECORD
pih2o-1.0.3.dist-info/WHEEL
pih2o-1.0.3.dist-info/entry_points.txt
pih2o-1.0.3.dist-info/metadata.json
pih2o-1.0.3.dist-info/top_level.txt
