Metadata-Version: 2.0
Name: pih2o
Version: 1.0.3
Summary: An automatic plant watering application in pure Python for the Raspberry Pi.
Home-page: https://github.com/anxuae/piH2O
Author: Antoine Rousseaux
Author-email: UNKNOWN
License: MIT license
Download-URL: https://github.com/anxuae/piH2O.git
Keywords: Raspberry Pi,Plant,Watering
Platform: unix
Platform: linux
Classifier: Development Status :: 2 - Pre-Alpha
Classifier: Environment :: Other Environment
Classifier: Intended Audience :: Developers
Classifier: Intended Audience :: End Users/Desktop
Classifier: License :: OSI Approved :: MIT License
Classifier: Operating System :: POSIX :: Linux
Classifier: Programming Language :: Python :: 2.7
Classifier: Programming Language :: Python :: 3.4
Classifier: Programming Language :: Python :: 3.5
Classifier: Framework :: Flask
Classifier: Topic :: Home Automation
Classifier: Topic :: Scientific/Engineering :: Atmospheric Science
Requires-Dist: RPi.GPIO
Requires-Dist: adafruit-ads1x15
Requires-Dist: blinker
Requires-Dist: croniter
Requires-Dist: flask
Requires-Dist: flask-restful
Requires-Dist: flask-sqlalchemy
